{
  "data": {
    "workorders": [
      {
        "actual_inspector": 1020,
        "administrator_id": 408,
        "approve_status": 3,
        "created_by": 1020,
        "current_operation_plan": [
          {
            "type_id": 2,
            "assigned": 0,
            "allocated": 0,
            "contract_id": 152,
            "contractor_id": 16,
            "administration_id": 408
          },
          {
            "type_id": 1,
            "assigned": 0,
            "allocated": 0,
            "contract_id": 130,
            "contractor_id": 4,
            "administration_id": 408
          },
          {
            "type_id": 3,
            "assigned": 0,
            "allocated": 0,
            "contract_id": 152,
            "contractor_id": 16,
            "administration_id": 408
          },
          {
            "type_id": "1",
            "assigned": "0",
            "allocated": "0",
            "contract_id": 257,
            "contractor_id": 22
          }
        ],
        "domain_examination_form_template_id": 7,
        "end_lat": "24.76807841993328",
        "end_lng": "46.66569165264988",
        "fail_reson_id": 65,
        "id": 39,
        "is_heavy": false,
        "is_morning": true,
        "schedule_to": 1020,
        "school_id": 38744,
        "sector_id": 32
      },
      {
        "actual_inspector": 207,
        "administrator_id": 408,
        "approve_status": 3,
        "created_by": 207,
        "current_operation_plan": [
          {
            "type_id": 2,
            "assigned": 0,
            "allocated": 0,
            "contract_id": 152,
            "contractor_id": 16,
            "administration_id": 408
          },
          {
            "type_id": 1,
            "assigned": 0,
            "allocated": 0,
            "contract_id": 130,
            "contractor_id": 4,
            "administration_id": 408
          },
          {
            "type_id": 3,
            "assigned": 0,
            "allocated": 0,
            "contract_id": 152,
            "contractor_id": 16,
            "administration_id": 408
          },
          {
            "type_id": "1",
            "assigned": "0",
            "allocated": "0",
            "contract_id": 257,
            "contractor_id": 22
          }
        ],
        "domain_examination_form_template_id": 2,
        "end_lat": "17.154574239461564",
        "end_lng": "42.65010304050446",
        "fail_reson_id": 61,
        "id": 40,
        "is_heavy": true,
        "is_morning": true,
        "schedule_to": 207,
        "school_id": 38789,
        "sector_id": 32
      },
      {
        "actual_inspector": 404,
        "administrator_id": 408,
        "approve_status": 4,
        "created_by": 207,
        "current_operation_plan": [
          {
            "type_id": 2,
            "assigned": 0,
            "allocated": 0,
            "contract_id": 152,
            "contractor_id": 16,
            "administration_id": 408
          },
          {
            "type_id": 1,
            "assigned": 0,
            "allocated": 0,
            "contract_id": 130,
            "contractor_id": 4,
            "administration_id": 408
          },
          {
            "type_id": 3,
            "assigned": 0,
            "allocated": 0,
            "contract_id": 152,
            "contractor_id": 16,
            "administration_id": 408
          }
        ],
        "domain_examination_form_template_id": 7,
        "end_lat": "17.147060644552035",
        "end_lng": "42.63087913127231",
        "fail_reson_id": null,
        "id": 24,
        "is_heavy": true,
        "is_morning": true,
        "schedule_to": 404,
        "school_id": 38744,
        "sector_id": 32
      },
      {
        "actual_inspector": 1020,
        "administrator_id": 408,
        "approve_status": 3,
        "created_by": 1020,
        "current_operation_plan": [
          {
            "type_id": 2,
            "assigned": 0,
            "allocated": 0,
            "contract_id": 152,
            "contractor_id": 16,
            "administration_id": 408
          },
          {
            "type_id": 1,
            "assigned": 0,
            "allocated": 0,
            "contract_id": 130,
            "contractor_id": 4,
            "administration_id": 408
          },
          {
            "type_id": 3,
            "assigned": 0,
            "allocated": 0,
            "contract_id": 152,
            "contractor_id": 16,
            "administration_id": 408
          },
          {
            "type_id": "1",
            "assigned": "0",
            "allocated": "0",
            "contract_id": 257,
            "contractor_id": 22
          }
        ],
        "domain_examination_form_template_id": 2,
        "end_lat": "24.76807841993328",
        "end_lng": "46.66569165264988",
        "fail_reson_id": 44,
        "id": 41,
        "is_heavy": false,
        "is_morning": true,
        "schedule_to": 1020,
        "school_id": 38789,
        "sector_id": 32
      },
      {
        "actual_inspector": 376,
        "administrator_id": 408,
        "approve_status": 4,
        "created_by": 207,
        "current_operation_plan": [
          {
            "type_id": 2,
            "assigned": 0,
            "allocated": 0,
            "contract_id": 152,
            "contractor_id": 16,
            "administration_id": 408
          },
          {
            "type_id": 1,
            "assigned": 0,
            "allocated": 0,
            "contract_id": 130,
            "contractor_id": 4,
            "administration_id": 408
          },
          {
            "type_id": 3,
            "assigned": 0,
            "allocated": 0,
            "contract_id": 152,
            "contractor_id": 16,
            "administration_id": 408
          }
        ],
        "domain_examination_form_template_id": 7,
        "end_lat": "16.912116719473662",
        "end_lng": "42.591324210823025",
        "fail_reson_id": null,
        "id": 25,
        "is_heavy": true,
        "is_morning": true,
        "schedule_to": 376,
        "school_id": 38744,
        "sector_id": 32
      },
      {
        "actual_inspector": 1020,
        "administrator_id": 408,
        "approve_status": 3,
        "created_by": 1020,
        "current_operation_plan": [
          {
            "type_id": 2,
            "assigned": 0,
            "allocated": 0,
            "contract_id": 152,
            "contractor_id": 16,
            "administration_id": 408
          },
          {
            "type_id": 1,
            "assigned": 0,
            "allocated": 0,
            "contract_id": 130,
            "contractor_id": 4,
            "administration_id": 408
          },
          {
            "type_id": 3,
            "assigned": 0,
            "allocated": 0,
            "contract_id": 152,
            "contractor_id": 16,
            "administration_id": 408
          },
          {
            "type_id": "1",
            "assigned": "0",
            "allocated": "0",
            "contract_id": 257,
            "contractor_id": 22
          }
        ],
        "domain_examination_form_template_id": 2,
        "end_lat": "24.76807841993328",
        "end_lng": "46.66569165264988",
        "fail_reson_id": 44,
        "id": 42,
        "is_heavy": false,
        "is_morning": true,
        "schedule_to": 1020,
        "school_id": 38789,
        "sector_id": 32
      },
      {
        "actual_inspector": 376,
        "administrator_id": 408,
        "approve_status": 4,
        "created_by": 207,
        "current_operation_plan": [
          {
            "type_id": 2,
            "assigned": 0,
            "allocated": 0,
            "contract_id": 152,
            "contractor_id": 16,
            "administration_id": 408
          },
          {
            "type_id": 1,
            "assigned": 0,
            "allocated": 0,
            "contract_id": 130,
            "contractor_id": 4,
            "administration_id": 408
          },
          {
            "type_id": 3,
            "assigned": 0,
            "allocated": 0,
            "contract_id": 152,
            "contractor_id": 16,
            "administration_id": 408
          }
        ],
        "domain_examination_form_template_id": 2,
        "end_lat": "16.912245877531113",
        "end_lng": "42.59136153305858",
        "fail_reson_id": null,
        "id": 26,
        "is_heavy": true,
        "is_morning": true,
        "schedule_to": 376,
        "school_id": 38789,
        "sector_id": 32
      },
      {
        "actual_inspector": 485,
        "administrator_id": 426,
        "approve_status": 5,
        "created_by": 123,
        "current_operation_plan": [
          {
            "type_id": 1,
            "assigned": 0,
            "allocated": 0,
            "contract_id": 121,
            "contractor_id": 2,
            "administration_id": 426
          },
          {
            "type_id": 1,
            "assigned": 0,
            "allocated": 0,
            "contract_id": 127,
            "contractor_id": 4,
            "administration_id": 426
          },
          {
            "type_id": 3,
            "assigned": 0,
            "allocated": 0,
            "contract_id": 153,
            "contractor_id": 17,
            "administration_id": 426
          },
          {
            "type_id": 2,
            "assigned": 0,
            "allocated": 0,
            "contract_id": 153,
            "contractor_id": 17,
            "administration_id": 426
          },
          {
            "type_id": 1,
            "assigned": 0,
            "allocated": 0,
            "contract_id": 137,
            "contractor_id": 7,
            "administration_id": 426
          }
        ],
        "domain_examination_form_template_id": 7,
        "end_lat": "26.375588499026055",
        "end_lng": "44.021935677878076",
        "fail_reson_id": null,
        "id": 43,
        "is_heavy": false,
        "is_morning": true,
        "schedule_to": 485,
        "school_id": 38726,
        "sector_id": 31
      },
      {
        "actual_inspector": 480,
        "administrator_id": 426,
        "approve_status": 5,
        "created_by": 123,
        "current_operation_plan": [
          {
            "type_id": 1,
            "assigned": 0,
            "allocated": 0,
            "contract_id": 121,
            "contractor_id": 2,
            "administration_id": 426
          },
          {
            "type_id": 1,
            "assigned": 0,
            "allocated": 0,
            "contract_id": 127,
            "contractor_id": 4,
            "administration_id": 426
          },
          {
            "type_id": 3,
            "assigned": 0,
            "allocated": 0,
            "contract_id": 153,
            "contractor_id": 17,
            "administration_id": 426
          },
          {
            "type_id": 2,
            "assigned": 0,
            "allocated": 0,
            "contract_id": 153,
            "contractor_id": 17,
            "administration_id": 426
          },
          {
            "type_id": 1,
            "assigned": 0,
            "allocated": 0,
            "contract_id": 137,
            "contractor_id": 7,
            "administration_id": 426
          }
        ],
        "domain_examination_form_template_id": 7,
        "end_lat": "26.37557499487684",
        "end_lng": "44.02190554882175",
        "fail_reson_id": null,
        "id": 44,
        "is_heavy": false,
        "is_morning": true,
        "schedule_to": 480,
        "school_id": 38726,
        "sector_id": 31
      },
      {
        "actual_inspector": 361,
        "administrator_id": 426,
        "approve_status": 5,
        "created_by": 123,
        "current_operation_plan": [
          {
            "type_id": 1,
            "assigned": 0,
            "allocated": 0,
            "contract_id": 121,
            "contractor_id": 2,
            "administration_id": 426
          },
          {
            "type_id": 1,
            "assigned": 0,
            "allocated": 0,
            "contract_id": 127,
            "contractor_id": 4,
            "administration_id": 426
          },
          {
            "type_id": 3,
            "assigned": 0,
            "allocated": 0,
            "contract_id": 153,
            "contractor_id": 17,
            "administration_id": 426
          },
          {
            "type_id": 2,
            "assigned": 0,
            "allocated": 0,
            "contract_id": 153,
            "contractor_id": 17,
            "administration_id": 426
          },
          {
            "type_id": 1,
            "assigned": 0,
            "allocated": 0,
            "contract_id": 137,
            "contractor_id": 7,
            "administration_id": 426
          }
        ],
        "domain_examination_form_template_id": 7,
        "end_lat": "26.37514853449384",
        "end_lng": "44.022395671052486",
        "fail_reson_id": null,
        "id": 45,
        "is_heavy": false,
        "is_morning": true,
        "schedule_to": 361,
        "school_id": 38726,
        "sector_id": 31
      }
    ]
  }
}